asbestos/__init__.py
asbestos/asbestos.py
asbestos/exceptions.py
asbestos-1.6.1.dist-info/LICENSE.md
asbestos-1.6.1.dist-info/METADATA
asbestos-1.6.1.dist-info/WHEEL
asbestos-1.6.1.dist-info/RECORD
